tradevps-0.2.0.dist-info/METADATA
tradevps-0.2.0.dist-info/WHEEL
tradevps-0.2.0.dist-info/entry_points.txt
tradevps-0.2.0.dist-info/licenses/LICENSE
tradevps/__init__.py
tradevps/client.py
tradevps/exceptions.py
tradevps/models/__init__.py
tradevps/models/account.py
tradevps/models/auth.py
tradevps/models/notifications.py
tradevps/models/tokens.py
tradevps/resources/__init__.py
tradevps/resources/account.py
tradevps/resources/auth.py
tradevps/resources/base.py
tradevps/resources/modules/__init__.py
tradevps/resources/modules/account/__init__.py
tradevps/resources/modules/account/notifications.py
tradevps/resources/modules/account/profile.py
tradevps/resources/modules/account/tokens.py
tradevps-0.2.0.dist-info/RECORD
