Metadata-Version: 2.1
Name: tradevps
Version: 0.2.0
Summary: Official Python client for TradeVPS APIs
Author-Email: TradeVPS <dev@tradevps.net>, moezehdev <hi@moezeh.dev>
License: MIT
Requires-Python: >=3.8
Requires-Dist: requests<3.0.0,>=2.31.0
Requires-Dist: pydantic<3.0.0,>=2.5.0
Requires-Dist: python-dotenv<2.0.0,>=1.0.0
Requires-Dist: urllib3<2.3.0,>=2.0.0
Requires-Dist: email-validator<3.0.0,>=2.1.0
